foliant/preprocessors/bindsympli.py
foliantcontrib.bindsympli-1.0.14.data/data/bin/get_sympli_img_urls.js
foliantcontrib.bindsympli-1.0.14.dist-info/LICENSE
foliantcontrib.bindsympli-1.0.14.dist-info/METADATA
foliantcontrib.bindsympli-1.0.14.dist-info/WHEEL
foliantcontrib.bindsympli-1.0.14.dist-info/top_level.txt
foliantcontrib.bindsympli-1.0.14.dist-info/RECORD
