Metadata-Version: 2.1
Name: foliantcontrib.bindsympli
Version: 1.0.14
Summary: Sympli integration preprocessor for Foliant.
Home-page: https://github.com/foliant-docs/foliantcontrib.bindsympli
Author: Artemy Lomov
Author-email: artemy@lomov.ru
License: MIT
Platform: UNKNOWN
Classifier: Development Status :: 5 - Production/Stable
Classifier: Environment :: Console
Classifier: Intended Audience :: Developers
Classifier: License :: OSI Approved :: MIT License
Classifier: Operating System :: POSIX :: Linux
Classifier: Operating System :: MacOS
Classifier: Programming Language :: Python
Classifier: Topic :: Documentation
Classifier: Topic :: Utilities
Requires-Dist: foliant (>=1.0.8)
